README.rst
setup.py
src/waldur_aws/__init__.py
src/waldur_aws/admin.py
src/waldur_aws/apps.py
src/waldur_aws/backend.py
src/waldur_aws/cost_tracking.py
src/waldur_aws/executors.py
src/waldur_aws/extension.py
src/waldur_aws/filters.py
src/waldur_aws/models.py
src/waldur_aws/serializers.py
src/waldur_aws/tasks.py
src/waldur_aws/urls.py
src/waldur_aws/views.py
src/waldur_aws.egg-info/PKG-INFO
src/waldur_aws.egg-info/SOURCES.txt
src/waldur_aws.egg-info/dependency_links.txt
src/waldur_aws.egg-info/entry_points.txt
src/waldur_aws.egg-info/not-zip-safe
src/waldur_aws.egg-info/requires.txt
src/waldur_aws.egg-info/top_level.txt
src/waldur_aws/management/__init__.py
src/waldur_aws/management/commands/__init__.py
src/waldur_aws/management/commands/export_ami_catalog.py
src/waldur_aws/management/commands/import_ami_catalog.py
src/waldur_aws/migrations/0001_initial.py
src/waldur_aws/migrations/__init__.py